bdbotstest/__init__.py
bdbotstest/help.py
bdbotstest-1.0.1.dist-info/LICENSE
bdbotstest-1.0.1.dist-info/METADATA
bdbotstest-1.0.1.dist-info/WHEEL
bdbotstest-1.0.1.dist-info/entry_points.txt
bdbotstest-1.0.1.dist-info/top_level.txt
bdbotstest-1.0.1.dist-info/RECORD
