Metadata-Version: 2.1
Name: bdbotstest
Version: 1.0.1
Summary: A bdbots test module
Home-page: https://github.com/nafismuhtadi929/bdbotstest
Author: BDBOTSTEST
Author-email: bdbotstest@admin.com
Classifier: Programming Language :: Python :: 3
Classifier: License :: OSI Approved :: MIT License
Classifier: Operating System :: OS Independent
Requires-Python: >=3.6
License-File: LICENSE
